{
  "version": "v5.20.0",
  "gitCommit": "efc2e94ae4c8acb95f9b60c27d1f84a5b13e1e0a",
  "branch": "work/v5.0.0",
  "title": "波ドリブン(v5.20.0)",
  "timestamp": "2026-06-12T16:25:00+09:00",
  "result": "gated deploy完了(建玉0・窓外・WAX停止→復帰・master OFF→ON→flat・凍結5 SHA三者一致・pid=port一致)。仮想限定(source=wave・wave_live=off封印)。実波トリガー初回発火は観測待ち",
  "summary": "第三の起動経路=波。(a)棚ブレイク=H1/M15棚実体抜け+三層一致 (b)反転ターン=junオーバーシュート移植。棚強度=mizushima水平線スコア。介入検知器=出口感度ブースト専用(入口非参照grep 0件)。被り調停3則。kill flag=wave_drive往復試験済(off→on)。リプレイ答え合わせ(6/12未明98p下落→売り候補6+反転買い3)合格済",
  "tanaka": "段A=本体(a)-(f)全○・CHANGELOG scp漏れ差し戻し→即追完合格。段B=合格(申し送り3件=ECBクラスタが発言系を食う/JP英名声明のBOJ落ち/★1未来日バッジ文言→設計書§6.95に記録)。",
  "state": {
    "master": "ON",
    "positions": 0,
    "arms": "9本(全lots=1.0・fc#473は本数ルール整理=効方向flip起因・485は14:50消費済み)",
    "guardian": "enabled",
    "wax": "復帰済(autoDelegate=true)",
    "wave": "wave_drive=on/wave_live=off"
  },
  "backups": {
    "pre-ben2": "C:\\Users\\wakui\\backups\\pre-ben2 (6/10 22:4x・trades.db 127.9MB integrity ok)",
    "pre-final": "C:\\Users\\wakui\\backups\\pre-final (6/11 11:44・trades.db 130.0MB integrity ok)",
    "restore": "restore-ben2.bat / restore-final.bat 両方(full|dist|test) test合格"
  },
  "ledger_rule": "デプロイ台帳は本体リポジトリとfx-shotsの両方を毎回更新しgitCommitを必ず記載する",
  "frozen": {
    "activeExit": "8329e65238268a6683df85936a1452b281e5db46aa1eb54cf4a2e903d96e6b11",
    "fishermanTrader": "f7cb31d6360af32b0d0089df7905f7ca5985db169126d999f3424bfec341b41e",
    "fishermanForecast": "2ad3dec80cf8ca13fac453870e2c7d6049c5015b7f7dd7d0e0c1df6d6b4727cf",
    "waxTrader": "31b7dd35a07947189bcc4635cd362244da6673c836169599f9567c3653c26b90",
    "waxForecast": "50df0a66f0d234438c32aa617ceda89653f4d9ead56ad5511bf9a934e26d0be1"
  },
  "builtAt": "2026-06-12T03:37:35Z"
}
